LICENSE
MANIFEST.in
README.md
setup.py
cyavro/__init__.py
cyavro/_cavro.pxd
cyavro/_cyavro.c
cyavro/_cyavro.pxd
cyavro/_cyavro.pyx
cyavro/dask_reader.py
cyavro/posixstdio.pxd
cyavro/test_utils.c
cyavro/test_utils.pyx
cyavro/version.py
cyavro.egg-info/PKG-INFO
cyavro.egg-info/SOURCES.txt
cyavro.egg-info/dependency_links.txt
cyavro.egg-info/top_level.txt
cyavro/osx/fmemopen.c
cyavro/osx/fmemopen.h
test/test_dask.py